revGigaChat/__init__.py
revGigaChat/revGigaChat.py
revGigaChat-1.4.dist-info/LICENSE
revGigaChat-1.4.dist-info/METADATA
revGigaChat-1.4.dist-info/WHEEL
revGigaChat-1.4.dist-info/top_level.txt
revGigaChat-1.4.dist-info/RECORD
